sql_smith/__init__.py
sql_smith/builder/__init__.py
sql_smith/builder/criteria_builder.py
sql_smith/builder/like_builder.py
sql_smith/capability/__init__.py
sql_smith/capability/can_union.py
sql_smith/capability/has_from.py
sql_smith/capability/has_limit.py
sql_smith/capability/has_offset.py
sql_smith/capability/has_order_by.py
sql_smith/capability/has_returning.py
sql_smith/capability/has_where.py
sql_smith/engine/__init__.py
sql_smith/engine/basic_engine.py
sql_smith/engine/common_engine.py
sql_smith/engine/mysql_engine.py
sql_smith/engine/postgres_engine.py
sql_smith/engine/sql_server_engine.py
sql_smith/engine/sqlite_engine.py
sql_smith/functions.py
sql_smith/interfaces/__init__.py
sql_smith/interfaces/criteria_interface.py
sql_smith/interfaces/engine_interface.py
sql_smith/interfaces/expression_interface.py
sql_smith/interfaces/query_interface.py
sql_smith/interfaces/statement_interface.py
sql_smith/partial/__init__.py
sql_smith/partial/criteria.py
sql_smith/partial/expression.py
sql_smith/partial/identifier.py
sql_smith/partial/like_begins.py
sql_smith/partial/like_contains.py
sql_smith/partial/like_ends.py
sql_smith/partial/listing.py
sql_smith/partial/literal.py
sql_smith/partial/parameter/__init__.py
sql_smith/partial/parameter/bool_parameter.py
sql_smith/partial/parameter/null_parameter.py
sql_smith/partial/parameter/parameter.py
sql_smith/partial/qualified_identifier.py
sql_smith/query/__init__.py
sql_smith/query/abstract_query.py
sql_smith/query/delete_query.py
sql_smith/query/insert_query.py
sql_smith/query/mysql/__init__.py
sql_smith/query/mysql/insert_query.py
sql_smith/query/mysql/select_query.py
sql_smith/query/postgres/__init__.py
sql_smith/query/postgres/insert_query.py
sql_smith/query/postgres/update_query.py
sql_smith/query/query.py
sql_smith/query/select_query.py
sql_smith/query/sql_server/__init__.py
sql_smith/query/sql_server/delete_query.py
sql_smith/query/sql_server/select_query.py
sql_smith/query/union_query.py
sql_smith-1.1.2.dist-info/WHEEL
sql_smith-1.1.2.dist-info/METADATA
sql_smith-1.1.2.dist-info/RECORD
