Metadata-Version: 2.4
Name: sql-smith
Version: 1.1.2
Summary: sql-smith is an SQL query builder with zero dependencies and a fluent interface.
Keywords: sql-smith,query,builder,querybuilder,sql,mysql,sqlite,postgres,sqlserver,database
Author: Zumuta!
Author-email: Zumuta! <franky.braem@zumuta.be>
License-Expression: MIT
Classifier: License :: OSI Approved :: MIT License
Classifier: Development Status :: 5 - Production/Stable
Classifier: Intended Audience :: Developers
Classifier: Programming Language :: Python :: 3
Classifier: Programming Language :: Python :: 3.10
Classifier: Topic :: Software Development :: Libraries :: Python Modules
Classifier: Operating System :: OS Independent
Requires-Python: >=3.10.0
